{
    "name": "PRIVILEGES.AREAS.NAME",
    "description": "PRIVILEGES.AREAS.DESCRIPTION",
    "config": {
        "privileges": {
            "read": false,
            "create": false,
            "update": false,
            "delete": false
        },
        "menu": {
            "state": "triangular.mi-ssvq.admin-areas",
            "url": "/areas",
            "template": "<ssvq-area-maintainer></ssvq-area-maintainer>"
        },
        "_controllers": {
            "read": [
                "AreaController.*"
            ],
            "create": [
                "AreaController.save"
            ],
            "update": [
                "AreaController.save"
            ],
            "delete": [
                "AreaController.delete"
            ]
        }
    }
}